yashpyproject/__init__.py
yashpyproject-0.0.6.dist-info/LICENSE.txt
yashpyproject-0.0.6.dist-info/METADATA
yashpyproject-0.0.6.dist-info/WHEEL
yashpyproject-0.0.6.dist-info/top_level.txt
yashpyproject-0.0.6.dist-info/RECORD
